{"EditorX":-2949.824921292088,"EditorY":-2137.7068901882812,"EditorZ":0.2500000000000002,"Nodes":[{"NodeID":1,"X":-499.0,"Y":-99.0},{"NodeID":2,"X":629.0,"Y":-214.0},{"NodeID":4,"X":1258.0,"Y":-223.0},{"NodeID":5,"X":1694.0,"Y":-221.0},{"NodeID":12,"X":4619.0,"Y":-336.0},{"NodeID":13,"X":5287.0,"Y":-364.0},{"NodeID":14,"X":5849.0,"Y":-375.0},{"NodeID":3,"X":1046.0,"Y":-176.0},{"NodeID":6,"X":2165.0,"Y":-248.0},{"NodeID":7,"X":2518.0,"Y":-246.0},{"NodeID":8,"X":4164.0,"Y":-351.0},{"NodeID":18,"X":6212.0,"Y":-208.0},{"NodeID":15,"X":6212.0,"Y":-477.0},{"NodeID":10,"X":6688.0,"Y":-303.0},{"NodeID":11,"X":-218.0,"Y":-632.0},{"NodeID":17,"X":5644.0,"Y":-311.0},{"NodeID":19,"X":4939.0,"Y":-340.0},{"NodeID":20,"X":-171.0,"Y":-323.0},{"NodeID":21,"X":6685.0,"Y":-469.0},{"NodeID":22,"X":2969.0,"Y":-251.0},{"NodeID":23,"X":4167.0,"Y":-93.0},{"NodeID":24,"X":3451.0,"Y":-220.0},{"NodeID":27,"X":3782.0,"Y":-201.0},{"NodeID":28,"X":-185.0,"Y":-134.0},{"NodeID":29,"X":73.0,"Y":-147.0},{"NodeID":30,"X":383.0,"Y":-171.0}]}